authlink/__init__.py
authlink/adapter.py
authlink/auth_backends.py
authlink/middleware.py
authlink/models.py
authlink/utils.py
authlink/views.py
authlink/api/__init__.py
authlink/api/rest_framework/__init__.py
authlink/api/rest_framework/serializers.py
authlink/api/rest_framework/views.py
authlink/migrations/0001_initial.py
authlink/migrations/__init__.py
django_authlink-1.0.0.dist-info/LICENSE
django_authlink-1.0.0.dist-info/METADATA
django_authlink-1.0.0.dist-info/WHEEL
django_authlink-1.0.0.dist-info/top_level.txt
django_authlink-1.0.0.dist-info/RECORD
