Metadata-Version: 2.1
Name: django-authlink
Version: 1.0.0
Summary: Provides magic-link authentication for Django web apps
Home-page: https://github.com/lukeburden/django-authlink
Author: Luke Burden
Author-email: lukeburden@gmail.com
License: MIT
Platform: UNKNOWN
Classifier: Development Status :: 5 - Production/Stable
Classifier: Environment :: Web Environment
Classifier: Intended Audience :: Developers
Classifier: License :: OSI Approved :: MIT License
Classifier: Operating System :: OS Independent
Classifier: Programming Language :: Python
Classifier: Programming Language :: Python :: 3
Classifier: Framework :: Django
Requires-Dist: django (<4,>=2)
Requires-Dist: django-ipware (>=2)
Requires-Dist: djangorestframework (>=3)
